LICENSE
MANIFEST.in
README.rst
requirements.txt
setup.py
django_dynamodb2_sessions.egg-info/PKG-INFO
django_dynamodb2_sessions.egg-info/SOURCES.txt
django_dynamodb2_sessions.egg-info/dependency_links.txt
django_dynamodb2_sessions.egg-info/requires.txt
django_dynamodb2_sessions.egg-info/top_level.txt
dynamodb2_sessions/__init__.py
dynamodb2_sessions/models.py
dynamodb2_sessions/tests.py
dynamodb2_sessions/backends/__init__.py
dynamodb2_sessions/backends/cached_dynamodb.py
dynamodb2_sessions/backends/dynamodb.py
dynamodb2_sessions/management/__init__.py
dynamodb2_sessions/management/commands/__init__.py
dynamodb2_sessions/management/commands/clearsessions.py
dynamodb2_sessions/management/commands/delete_sessions.py