Metadata-Version: 1.1
Name: django-dynamodb2-sessions
Version: 0.2
Summary: Sessions backend dedicated for Django uses Amazon DynamoDB v.2
Home-page: https://github.com/Solution4Future/django-dynamodb2-sessions
Author: Justyna Zarna
Author-email: justyna.zarna@solution4future.com
License: BSD License
Platform: any
Classifier: Development Status :: 4 - Beta
Classifier: Intended Audience :: Developers
Classifier: License :: OSI Approved :: BSD License
Classifier: Natural Language :: English
Classifier: Operating System :: OS Independent
Classifier: Programming Language :: Python
Classifier: Environment :: Web Environment
